tests/__init__.py
tests/test_ffdd.py
codon_degeneracy-0.1.3.dist-info/LICENSE.txt
codon_degeneracy-0.1.3.dist-info/METADATA
codon_degeneracy-0.1.3.dist-info/WHEEL
codon_degeneracy-0.1.3.dist-info/top_level.txt
codon_degeneracy-0.1.3.dist-info/RECORD
