Metadata-Version: 2.1
Name: codon-degeneracy
Version: 0.1.3
Summary: 
Home-page: https://github.com/nickmachnik/codon-degeneracy.git
Author: Nick Noel Machnik
Author-email: nick.machnik@gmail.com
License: UNKNOWN
Platform: UNKNOWN
Classifier: Programming Language :: Python :: 3
Classifier: License :: OSI Approved :: MIT License
Classifier: Operating System :: OS Independent
Requires-Dist: numpy (>=1.8.0)
Requires-Dist: scikit-bio
Requires-Dist: biopython
